grom/__init__.py
grom/components/__init__.py
grom/components/frame/__init__.py
grom/components/frame/base.py
grom/components/frame/borders.py
grom/components/line/__init__.py
grom/components/line/base.py
grom/components/progress_bar/__init__.py
grom/components/progress_bar/base.py
grom/components/progress_bar/formatters.py
grom/components/spin/__init__.py
grom/components/spin/base.py
grom/components/spin/formatters.py
grom/console/__init__.py
grom/console/console.py
grom/console/help_formatter.py
grom/console/validate.py
grom/containers/__init__.py
grom/formatters/__init__.py
grom/formatters/filler.py
grom/formatters/format.py
grom/formatters/label.py
grom/formatters/spinner.py
grom/formatters/text.py
grom/theme/__init__.py
grom/tools/__init__.py
grom/tools/colors.py
grom/tools/singleton.py
grom-0.0.3.dist-info/METADATA
grom-0.0.3.dist-info/WHEEL
grom-0.0.3.dist-info/entry_points.txt
grom-0.0.3.dist-info/RECORD
